zrcl/app_pandoc.py
zrcl/base64_image.py
zrcl/bit_operation.py
zrcl/cls_inheritance.py
zrcl/crack_zip_password.py
zrcl/does_nothing.py
zrcl/ext.py
zrcl/ext_cryptography.py
zrcl/ext_discord.py
zrcl/ext_easyocr.py
zrcl/ext_hashlib.py
zrcl/ext_json.py
zrcl/ext_keyring.py
zrcl/ext_logging.py
zrcl/ext_moviepy.py
zrcl/ext_os.py
zrcl/ext_pillow.py
zrcl/ext_pygetwindow.py
zrcl/ext_pyscreeze.py
zrcl/ext_random.py
zrcl/ext_re.py
zrcl/ext_screeninfo.py
zrcl/ext_string.py
zrcl/ext_subprocess.py
zrcl/ext_time.py
zrcl/ext_typing.py
zrcl/ext_yaml.py
zrcl/file.py
zrcl/github.py
zrcl/markdown.py
zrcl/mediawiki_parser.py
zrcl/png_zip.py
zrcl/terminal_ui.py
zrcl/text_parsing.py
zrcl/tool_btype.py
zrcl/tool_coord_1.py
zrcl/tool_runner.py
zrcl/tool_sysinfo.py
zrcl/win32wnd.py
zrcl/beta_desktop_automation/__init__.py
zrcl/beta_desktop_automation/feature_cropper.py
zrcl/beta_desktop_automation/region_marker.py
zrcl-0.4.5.dist-info/METADATA
zrcl-0.4.5.dist-info/WHEEL
zrcl-0.4.5.dist-info/entry_points.txt
zrcl-0.4.5.dist-info/licenses/LICENSE
zrcl-0.4.5.dist-info/RECORD
