Metadata-Version: 2.3
Name: zrcl
Version: 0.4.5
Summary: Zack's common reusable library
Author-email: ZackaryW <36378555+ZackaryW@users.noreply.github.com>
License-File: LICENSE
Requires-Python: >=3.8
